{
	"id": "30b781dd-2986-4414-b0cf-57cf15e9379c",
	"name": "DevTraining",
	"values": [
		{
			"key": "BaseUri",
			"value": "http://k_krylov:7070/",
			"enabled": true
		},
		{
			"key": "Base_URL_IS",
			"value": "http://k_krylov:7071/",
			"enabled": false
		},
		{
			"key": "UserName",
			"value": "Supervisor",
			"enabled": true
		},
		{
			"key": "UserPassword",
			"value": "Supervisor",
			"enabled": true
		},
		{
			"key": "BPMCSRF",
			"value": "",
			"enabled": true
		},
		{
			"key": "Client_Id",
			"value": "",
			"enabled": false
		},
		{
			"key": "Client_Secret",
			"value": "",
			"enabled": false
		},
		{
			"key": "access_token",
			"value": "",
			"enabled": false
		},
		{
			"key": "EMAIL",
			"value": "",
			"enabled": true
		}
	],
	"_postman_variable_scope": "environment",
	"_postman_exported_at": "2021-08-03T10:16:41.356Z",
	"_postman_exported_using": "Postman/8.9.1"
}